{
  "checkpoint": "GAMMA",
  "timestamp": "2025-08-15T15:16:00.004709",
  "summary": {
    "total_tests": 7,
    "passed": 7,
    "failed": 0,
    "errors": 0,
    "skipped": 0,
    "success_rate": "100.0%"
  },
  "task_3_5_status": "COMPLETED",
  "task_3_6_status": "PASSED",
  "test_results": [
    {
      "test": "HR Login",
      "status": "PASSED",
      "details": "HR user authenticated successfully"
    },
    {
      "test": "Dashboard Stats Display",
      "status": "PASSED",
      "details": "All stats retrieved: 8 metrics"
    },
    {
      "test": "View All Properties",
      "status": "PASSED",
      "details": "Can view all 9 properties"
    },
    {
      "test": "View All Applications",
      "status": "PASSED",
      "details": "Can view all 30 applications from 4 properties"
    },
    {
      "test": "Filter Applications by Property",
      "status": "PASSED",
      "details": "Filtered 0 applications for property Test Property"
    },
    {
      "test": "Approve/Reject Applications",
      "status": "PASSED",
      "details": "HR can approve applications from any property"
    },
    {
      "test": "System-wide Visibility",
      "status": "PASSED",
      "details": "3/3 visibility checks passed"
    }
  ],
  "dashboard_stats": {
    "totalProperties": 9,
    "totalManagers": 4,
    "totalEmployees": 16,
    "pendingApplications": 9,
    "approvedApplications": 12,
    "totalApplications": 30,
    "activeEmployees": 16,
    "onboardingInProgress": 0
  }
}